tagforge/__init__.py
tagforge/models/__init__.py
tagforge/models/privacy/README.md
tagforge/models/privacy/__init__.py
tagforge/models/privacy/model.py
tagforge/models/privacy/optimized_privacy.json
tagforge/models/privacy/train.py
tagforge-0.1.0.dist-info/METADATA
tagforge-0.1.0.dist-info/WHEEL
tagforge-0.1.0.dist-info/licenses/LICENSE
tagforge-0.1.0.dist-info/RECORD
