Metadata-Version: 2.4
Name: tagforge
Version: 0.1.0
Summary: An open-source tool that uses LLMs + dspy to automatically generate smart, context-aware tags for blog posts, articles, and other written content
License: MIT
License-File: LICENSE
Author: Matt Struble
Author-email: 4325029+mattstruble@users.noreply.github.com
Requires-Python: <3.14,>=3.10
Classifier: License :: OSI Approved :: MIT License
Classifier: Programming Language :: Python :: 3
Classifier: Programming Language :: Python :: 3.10
Classifier: Programming Language :: Python :: 3.11
Classifier: Programming Language :: Python :: 3.12
Classifier: Programming Language :: Python :: 3.13
Requires-Dist: dspy (>=3.0.3,<4.0.0)
Requires-Dist: pydantic (>=2.11.7,<3.0.0)
Requires-Dist: tenacity (>=9.1.2,<10.0.0)
